[  {"body" : "A 16-year-old Brooklyn boy was arrested yesterday and charged with robbery in the $1,900 holdup of the driver of a soft-drink delivery truck in Cypress Hills, Queens, on Friday, the police said. Another youth involved in the robbery later shot and wounded a police officer before being arrested, according to the police. The officer is in fair" , "date" : "19830327" , "day_of_week_facet" : "Sunday" , "geo_facet" : ["NEW YORK CITY"] , "nytd_section_facet" : ["New York and Region"] , "page_facet" : "40" , "title" : "Teen-ager Held in Robbery" , "url" : "http:\/\/www.nytimes.com\/1983\/03\/27\/nyregion\/teen-ager-held-in-robbery.html"} , {"body" : "A plainclothes police officer was shot in a thigh yesterday as he wrestled with an armed teen-ager suspected of robbing a truck driver in Brooklyn, authorities said. The suspect - William Heosto, 18 years old, of 125 Nichols Avenue, Brooklyn - was arrested and charged with attempted murder, criminal use and possession of a firearm and robbery," , "date" : "19830326" , "day_of_week_facet" : "Saturday" , "geo_facet" : ["NEW YORK CITY"] , "nytd_section_facet" : ["New York and Region"] , "page_facet" : "27" , "title" : "THE CITY; Officer Wounded" , "url" : "http:\/\/www.nytimes.com\/1983\/03\/26\/nyregion\/the-city-officer-wounded.html"}]