{ "Atlanta Hawks" : [{ "wins": 25, "losses":57, "standing":{ "position":7, "division":"Central Division" }, "playoffs":{ "result":"", "team":"" } } ], "Boston Celtics" : [{ "wins": 36, "losses":46, "standing":{ "position":5, "division":"Atlantic Division" }, "playoffs":{ "result":"", "team":"" } } ], "Brooklyn Nets" : [{ "wins": 26, "losses":56, "standing":{ "position":6, "division":"Atlantic Division" }, "playoffs":{ "result":"", "team":"" } } ], "Charlotte Bobcats" : [{ "wins":, "losses":, "standing":{ "position":, "division":"" }, "playoffs":{ "result":"", "team":"" } } ], "Chicago Bulls" : [{ "wins": 15, "losses":67, "standing":{ "position":8, "division":"Central Division" }, "playoffs":{ "result":"", "team":"" } } ], "Cleveland Cavaliers" : [{ "wins": 30, "losses":52, "standing":{ "position":6, "division":"Central Division" }, "playoffs":{ "result":"", "team":"" } } ], "Dallas Mavericks" : [{ "wins": 53, "losses":29, "standing":{ "position":3, "division":"Midwest Division" }, "playoffs":{ "result":"Lost NBA Western Conference Semifinals (4-1)", "team":"San Antonio Spurs" } } ], "Denver Nuggets" : [{ "wins": 40, "losses":42, "standing":{ "position":6, "division":"Midwest Division" }, "playoffs":{ "result":"", "team":"" } } ], "Detroit Pistons" : [{ "wins": 32, "losses":50, "standing":{ "position":5, "division":"Central Division" }, "playoffs":{ "result":"", "team":"" } } ], "Golden State Warriors" : [{ "wins": 17, "losses":65, "standing":{ "position":7, "division":"Pacific Division" }, "playoffs":{ "result":"", "team":"" } } ], "Houston Rockets" : [{ "wins": 45, "losses":37, "standing":{ "position":5, "division":"Midwest Division" }, "playoffs":{ "result":"", "team":"" } } ], "Indiana Pacers" : [{ "wins": 41, "losses":41, "standing":{ "position":4, "division":"Central Division" }, "playoffs":{ "result":"Lost NBA Eastern Conference First Round (3-1)", "team":"Philadelphia 76ers" } } ], "Los Angeles Clippers" : [{ "wins": 31, "losses":51, "standing":{ "position":6, "division":"Pacific Division" }, "playoffs":{ "result":"", "team":"" } } ], "Los Angeles Lakers" : [{ "wins": 56, "losses":26, "standing":{ "position":1, "division":"Pacific Division" }, "playoffs":{ "result":"Won NBA Finals (4-1)", "team":"Philadelphia 76ers" } } ], "Memphis Grizzlies" : [{ "wins":, "losses":, "standing":{ "position":, "division":"" }, "playoffs":{ "result":"", "team":"" } } ], "Miami Heat" : [{ "wins": 50, "losses":32, "standing":{ "position":2, "division":"Atlantic Division" }, "playoffs":{ "result":"Lost NBA Eastern Conference First Round (3-0)", "team":"Charlotte Hornets" } } ], "Milwaukee Bucks" : [{ "wins": 52, "losses":30, "standing":{ "position":1, "division":"Central Division" }, "playoffs":{ "result":"Lost NBA Eastern Conference Finals (4-3)", "team":"Philadelphia 76ers" } } ], "Minnesota Timberwolves" : [{ "wins": 47, "losses":35, "standing":{ "position":4, "division":"Midwest Division" }, "playoffs":{ "result":"Lost NBA Western Conference First Round (3-1)", "team":"San Antonio Spurs" } } ], "New Orleans Hornets" : [{ "wins":, "losses":, "standing":{ "position":, "division":"" }, "playoffs":{ "result":"", "team":"" } } ], "New York Knicks" : [{ "wins": 48, "losses":34, "standing":{ "position":3, "division":"Atlantic Division" }, "playoffs":{ "result":"Lost NBA Eastern Conference First Round (3-2)", "team":"Toronto Raptors" } } ], "Oklahoma City Thunder" : [{ "wins":, "losses":, "standing":{ "position":, "division":"" }, "playoffs":{ "result":"", "team":"" } } ], "Orlando Magic" : [{ "wins": 43, "losses":39, "standing":{ "position":4, "division":"Atlantic Division" }, "playoffs":{ "result":"Lost NBA Eastern Conference First Round (3-1)", "team":"Milwaukee Bucks" } } ], "Philadelphia Seventy Sixers" : [{ "wins": 56, "losses":26, "standing":{ "position":1, "division":"Atlantic Division" }, "playoffs":{ "result":"Lost NBA Finals (4-1)", "team":"Los Angeles Lakers" } } ], "Phoenix Suns" : [{ "wins": 51, "losses":31, "standing":{ "position":3, "division":"Pacific Division" }, "playoffs":{ "result":"Lost NBA Western Conference First Round (3-1)", "team":"Sacramento Kings" } } ], "Portland Trailblazers" : [{ "wins": 50, "losses":32, "standing":{ "position":4, "division":"Pacific Division" }, "playoffs":{ "result":"Lost NBA Western Conference First Round (3-0)", "team":"Los Angeles Lakers" } } ], "Sacramento Kings" : [{ "wins": 55, "losses":27, "standing":{ "position":2, "division":"Pacific Division" }, "playoffs":{ "result":"Lost NBA Western Conference Semifinals (4-0)", "team":"Los Angeles Lakers" } } ], "San Antonio Spurs" : [{ "wins": 58, "losses":24, "standing":{ "position":1, "division":"Midwest Division" }, "playoffs":{ "result":"Lost NBA Western Conference Finals (4-0)", "team":"Los Angeles Lakers" } } ], "Toronto Raptors" : [{ "wins": 47, "losses":35, "standing":{ "position":2, "division":"Central Division" }, "playoffs":{ "result":"Lost NBA Eastern Conference Semifinals (4-3)", "team":"Philadelphia 76ers" } } ], "Utah Jazz" : [{ "wins": 53, "losses":29, "standing":{ "position":2, "division":"Midwest Division" }, "playoffs":{ "result":"Lost NBA Western Conference First Round (3-2)", "team":"Dallas Mavericks" } } ], "Washington Wizards" : [{ "wins": 19, "losses":63, "standing":{ "position":7, "division":"Atlantic Division" }, "playoffs":{ "result":"", "team":"" } } ] }